house_prices/__init__.py
house_prices/_label_encoder.py
house_prices/_min_support.py
house_prices/_missing_value_filter.py
house_prices/_mutual_info_filter.py
house_prices/_pipeline.py
house_prices-0.1.0.dist-info/WHEEL
house_prices-0.1.0.dist-info/METADATA
house_prices-0.1.0.dist-info/RECORD
